[
    {
        "id": 531227148632,
        "市场评估价": 376800,
        "起拍价格": 241600,
        "成交价格": 336600,
        "交易时间": "2016-05-21 10:03:09",
        "原始网站": "https://sf-item.taobao.com/sf_item/531227148632.htm?track_id=1133a53f-f5b6-4fa6-bd3c-caaba9418267",
        "是否成交": true,
        "竞拍人数": 8,
        "出价人数": 35,
        "地点": "江苏省徐州市泉山区",
        "所属小区": null,
        "省份": "江苏省",
        "城市": "徐州市",
        "区": "泉山区",
        "最靠近商圈": "三环西路板材市场",
        "建筑面积": 75.35,
        "单价": 4467.15,
        "is_processed": true,
        "detail_captured": true,
        "manual_checked": true
    },
    {
        "id": 530816930508,
        "市场评估价": null,
        "起拍价格": 489000,
        "成交价格": 530000,
        "交易时间": "2016/05/21 10:46:45",
        "原始网站": "https://sf-item.taobao.com/sf_item/530816930508.htm?track_id=95859d35-4662-4659-9c62-689f335e19d7",
        "是否成交": true,
        "竞拍人数": 0,
        "出价人数": 29,
        "地点": "新乡市建设东路16号绿营花园4号楼东3单元3层西户",
        "所属小区": "绿营花园",
        "省份": "河南省",
        "城市": "新乡市",
        "区": "牧野区",
        "最靠近商圈": "河师大",
        "建筑面积": 130.82,
        "单价": 4051.45,
        "is_processed": true,
        "detail_captured": true
    },
    {
        "id": 531194545796,
        "市场评估价": 0,
        "起拍价格": 803000,
        "成交价格": 1004000,
        "交易时间": "2016/05/21 10:40:36",
        "原始网站": "https://sf-item.taobao.com/sf_item/531194545796.htm?track_id=d384dc1c-b720-4c2e-a1ad-d968a4f0ed24",
        "是否成交": true,
        "竞拍人数": 0,
        "出价人数": 198,
        "地点": "无锡市锡山区君怡花苑32-602",
        "所属小区": "君怡花苑",
        "省份": "江苏省",
        "城市": "无锡市",
        "区": "锡山区",
        "最靠近商圈": "东亭",
        "建筑面积": null,
        "单价": 0,
        "is_processed": true,
        "detail_captured": true
    },
    {
        "id": 531161230279,
        "市场评估价": null,
        "起拍价格": 1295000,
        "成交价格": 1365000,
        "交易时间": "2016-05-21",
        "原始网站": "https://sf-item.taobao.com/sf_item/531161230279.htm?track_id=9d62b742-b4d8-4891-b062-beb125515e21",
        "是否成交": true,
        "竞拍人数": null,
        "出价人数": 15,
        "地点": "浙江省杭州市滨江区长河街道风景蝶院观园2幢1单元1102室",
        "所属小区": "风景蝶院观园",
        "省份": "浙江省",
        "城市": "杭州市",
        "区": "滨江区",
        "最靠近商圈": "长河商圈",
        "建筑面积": 86.96,
        "单价": 15695.94,
        "is_processed": true,
        "detail_captured": true
    }
]