[
    {
        "id": 650960686657,
        "市场评估价": 607966.33,
        "起拍价格": 340461.14,
        "成交价格": 340461.14,
        "交易时间": "2021-08-08 06:00:48",
        "原始网站": "https://sf-item.taobao.com/sf_item/650960686657.htm?track_id=3316eece-311a-46f3-96cd-8ac2b5c61b85",
        "是否成交": true,
        "竞拍人数": 1,
        "出价人数": 1,
        "地点": "四川省 成都市 金堂县 淮口镇定兴街206号附300号13栋1楼17号",
        "所属小区": null,
        "省份": "四川省",
        "城市": "成都市",
        "区": "金堂县",
        "最靠近商圈": "淮口镇",
        "建筑面积": 42.54,
        "单价": 8003.32,
        "is_processed": true,
        "detail_captured": true,
        "manual_checked": true
    },
    {
        "id": 650096994444,
        "市场评估价": 907400,
        "起拍价格": 635180,
        "成交价格": 635180,
        "交易时间": "2021/08/08 10:00:00",
        "原始网站": "https://sf-item.taobao.com/sf_item/650096994444.htm?track_id=9328425c-b754-4a3f-9717-8551d7aaadc9",
        "是否成交": true,
        "竞拍人数": 1,
        "出价人数": 1,
        "地点": "江苏省 徐州市 泉山区",
        "所属小区": "和平小区",
        "省份": "江苏省",
        "城市": "徐州市",
        "区": "泉山区",
        "最靠近商圈": "泉山万达广场",
        "建筑面积": 90.74,
        "单价": 7000.86,
        "is_processed": true,
        "detail_captured": true
    },
    {
        "id": 650644988351,
        "市场评估价": 6583600,
        "起拍价格": 2964412,
        "成交价格": 2964412,
        "交易时间": "2021/08/08 10:00:00",
        "原始网站": "https://sf-item.taobao.com/sf_item/650644988351.htm?track_id=d08b535d-1476-4625-aa1a-3468883d43b2",
        "是否成交": true,
        "竞拍人数": 1,
        "出价人数": 1,
        "地点": "江苏省 徐州市 泉山区 嘉和雅苑",
        "所属小区": "嘉和雅苑",
        "省份": "江苏省",
        "城市": "徐州市",
        "区": "泉山区",
        "最靠近商圈": "淮海西路",
        "建筑面积": 186.02,
        "单价": 15935.74,
        "is_processed": true,
        "detail_captured": true
    },
    {
        "id": 650405436080,
        "市场评估价": 4670262,
        "起拍价格": 2615346,
        "成交价格": 2855347,
        "交易时间": "2021-08-08 11:52:55",
        "原始网站": "https://sf-item.taobao.com/sf_item/650405436080.htm?track_id=1eed3f63-6c86-4e46-a19c-0be98e8bec2f",
        "是否成交": true,
        "竞拍人数": 47,
        "出价人数": 45,
        "地点": "湖南省 湘潭市 雨湖区 九华示范区九华大道1号正东佳源6号楼",
        "所属小区": "正东佳源",
        "省份": "湖南省",
        "城市": "湘潭市",
        "区": "雨湖区",
        "最靠近商圈": "九华示范区",
        "建筑面积": 0,
        "单价": 0,
        "is_processed": true,
        "detail_captured": true
    },
    {
        "id": 649915641699,
        "市场评估价": 437712,
        "起拍价格": 306398.4,
        "成交价格": 306398.4,
        "交易时间": "2021-08-08 10:00:00",
        "原始网站": "https://sf-item.taobao.com/sf_item/649915641699.htm?track_id=3bae198d-cc89-4517-b235-4cdd1b7b0056",
        "是否成交": true,
        "竞拍人数": 0,
        "出价人数": 0,
        "地点": "四川省 巴中市 南江县 米仓山大道文星段万利小区一号楼1-2-1号住宅",
        "所属小区": "万利小区",
        "省份": "四川省",
        "城市": "巴中市",
        "区": "南江县",
        "最靠近商圈": "文星段",
        "建筑面积": null,
        "单价": 0,
        "is_processed": true,
        "detail_captured": true
    },
    {
        "id": 651791375041,
        "市场评估价": null,
        "起拍价格": 267614.4,
        "成交价格": 267614.4,
        "交易时间": "2021-08-09",
        "原始网站": "https://sf-item.taobao.com/sf_item/651791375041.htm?track_id=8972c17e-ed0b-4ca9-8714-9facf5ed5987",
        "是否成交": true,
        "竞拍人数": null,
        "出价人数": 1,
        "地点": "贵州省遵义市汇川区宁波路文星苑6层1-601号",
        "所属小区": "文星苑",
        "省份": "贵州省",
        "城市": "遵义市",
        "区": "汇川区",
        "最靠近商圈": "文星苑",
        "建筑面积": 56.65,
        "单价": 4724.39,
        "is_processed": true,
        "detail_captured": true
    },
    {
        "id": 651814859280,
        "市场评估价": null,
        "起拍价格": 2579040,
        "成交价格": 2639040,
        "交易时间": "2021-08-08T10:16:50",
        "原始网站": "https://sf-item.taobao.com/sf_item/651814859280.htm?track_id=7b04b434-ceff-470a-aefa-d328aa1bebd6",
        "是否成交": true,
        "竞拍人数": null,
        "出价人数": 6,
        "地点": "陕西省 西安市 未央区 经济技术开发区凤城八路158号风景御园5幢31302室",
        "所属小区": "风景御园",
        "省份": "陕西省",
        "城市": "西安市",
        "区": "未央区",
        "最靠近商圈": "未央路商圈",
        "建筑面积": 140.56,
        "单价": 18760.27,
        "is_processed": true,
        "detail_captured": true
    },
    {
        "id": 650322726406,
        "市场评估价": 700420,
        "起拍价格": 700420,
        "成交价格": 860420,
        "交易时间": "2021-08-08 10:20:45",
        "原始网站": "https://sf-item.taobao.com/sf_item/650322726406.htm?track_id=c4b8e550-b589-43ac-b5b8-70dafb0f57bb",
        "是否成交": true,
        "竞拍人数": 76,
        "出价人数": 81,
        "地点": "江苏省淮安市涟水县涟水县丽晶首府小区4号楼1101室",
        "所属小区": "丽晶首府",
        "省份": "江苏省",
        "城市": "淮安市",
        "区": "涟水县",
        "最靠近商圈": "涟水主城区",
        "建筑面积": null,
        "单价": 0,
        "is_processed": true,
        "detail_captured": true
    },
    {
        "id": 649125328032,
        "市场评估价": null,
        "起拍价格": 581000,
        "成交价格": 601000,
        "交易时间": "2021/08/08 10:10:16",
        "原始网站": "https://sf-item.taobao.com/sf_item/649125328032.htm?track_id=c8a98758-d89c-4119-9cd3-afa7a351cacb",
        "是否成交": true,
        "竞拍人数": 5,
        "出价人数": 5,
        "地点": "福建省 泉州市 安溪县 凤城镇凤翔路37-1店",
        "所属小区": "凤翔花园",
        "省份": "福建省",
        "城市": "泉州市",
        "区": "安溪县",
        "最靠近商圈": "凤城商圈",
        "建筑面积": 45,
        "单价": 13355.56,
        "is_processed": true,
        "detail_captured": true,
        "manual_checked": true
    },
    {
        "id": 649289342662,
        "市场评估价": null,
        "起拍价格": 65374.08,
        "成交价格": 65374.08,
        "交易时间": "2021/08/09 00:23:00",
        "原始网站": "https://sf-item.taobao.com/sf_item/649289342662.htm?track_id=071853d6-ddf2-4e6c-b06a-71a1cdc67745",
        "是否成交": true,
        "竞拍人数": 1,
        "出价人数": 1,
        "地点": "云南省丽江市华坪县中心镇",
        "所属小区": "信合大厦",
        "省份": "云南省",
        "城市": "丽江市",
        "区": "华坪县",
        "最靠近商圈": "中心镇",
        "建筑面积": 29.85,
        "单价": 2189.19,
        "is_processed": true,
        "detail_captured": true
    },
    {
        "id": 651490690696,
        "市场评估价": null,
        "起拍价格": 1203500,
        "成交价格": 1423500,
        "交易时间": "2021-08-08",
        "原始网站": "https://sf-item.taobao.com/sf_item/651490690696.htm?track_id=e060ffc2-3fe3-43ca-bf44-12c2e06c793c",
        "是否成交": true,
        "竞拍人数": 56,
        "出价人数": 56,
        "地点": "黑龙江省 哈尔滨市 南岗区 和兴小区B栋1单元2层2号",
        "所属小区": "和兴小区",
        "省份": "黑龙江省",
        "城市": "哈尔滨市",
        "区": "南岗区",
        "最靠近商圈": "和兴商圈",
        "建筑面积": 189.86,
        "单价": 7500.08,
        "is_processed": true,
        "detail_captured": true
    },
    {
        "id": 649478812644,
        "市场评估价": 1122900,
        "起拍价格": 909549,
        "成交价格": 940549,
        "交易时间": "2021-08-08 11:00:00",
        "原始网站": "https://sf-item.taobao.com/sf_item/649478812644.htm?track_id=7f141910-db51-45a3-9231-296c59c964d5",
        "是否成交": true,
        "竞拍人数": 31,
        "出价人数": 31,
        "地点": "新疆维吾尔自治区 乌鲁木齐市 新市区 常州街111号新天润国际社区（三期A区）37栋3层3单元302室",
        "所属小区": "新天润国际社区",
        "省份": "新疆维吾尔自治区",
        "城市": "乌鲁木齐市",
        "区": "新市区",
        "最靠近商圈": "苏州路商圈",
        "建筑面积": 139.41,
        "单价": 6744.6,
        "is_processed": true,
        "detail_captured": true
    },
    {
        "id": 650193958231,
        "市场评估价": 2631346.9,
        "起拍价格": 2631346.9,
        "成交价格": 2681346.9,
        "交易时间": "2021-08-08T10:09:40",
        "原始网站": "https://sf-item.taobao.com/sf_item/650193958231.htm?track_id=c1aa6a1f-4533-4c62-bb29-92f2ef2730d8",
        "是否成交": true,
        "竞拍人数": 6,
        "出价人数": 6,
        "地点": "北京市昌平区回龙观镇天龙苑小区",
        "所属小区": "天龙苑",
        "省份": "北京",
        "城市": "北京",
        "区": "昌平区",
        "最靠近商圈": "回龙观",
        "建筑面积": 430.05,
        "单价": 6233.57,
        "is_processed": true,
        "detail_captured": true
    },
    {
        "id": 649501284003,
        "市场评估价": 3167267,
        "起拍价格": 2217086.9,
        "成交价格": 2497086.9,
        "交易时间": "2021/08/08 10:27:07",
        "原始网站": "https://sf-item.taobao.com/sf_item/649501284003.htm?track_id=3c4a47c4-8745-44c2-8782-1b6efe22e766",
        "是否成交": true,
        "竞拍人数": 0,
        "出价人数": 27,
        "地点": "辽宁省 大连市 西岗区 华泰街29号行政街号-16（建筑号D2号）",
        "所属小区": "华泰小区",
        "省份": "辽宁省",
        "城市": "大连市",
        "区": "西岗区",
        "最靠近商圈": "奥林匹克广场商圈",
        "建筑面积": 217.77,
        "单价": 11466.62,
        "is_processed": true,
        "detail_captured": true,
        "manual_checked": true
    },
    {
        "id": 651793335380,
        "市场评估价": 5502500,
        "起拍价格": 3521600,
        "成交价格": 3521600,
        "交易时间": "2021/08/08 10:04:08",
        "原始网站": "https://sf-item.taobao.com/sf_item/651793335380.htm?track_id=9b4428c8-602b-4737-8c08-d67d7b56d6b9",
        "是否成交": true,
        "竞拍人数": 1,
        "出价人数": 1,
        "地点": "湖北省武汉市武昌区东湖路138号秀水公寓住宅14层1607室",
        "所属小区": "秀水公寓",
        "省份": "湖北省",
        "城市": "武汉市",
        "区": "武昌区",
        "最靠近商圈": "东湖路",
        "建筑面积": 174.13,
        "单价": 20224.42,
        "is_processed": true,
        "detail_captured": true
    },
    {
        "id": 650637759307,
        "市场评估价": null,
        "起拍价格": null,
        "成交价格": 1200000,
        "交易时间": "2021/08/08 10:00:00",
        "原始网站": "https://sf-item.taobao.com/sf_item/650637759307.htm?track_id=1f6cd88f-6e22-40bc-b296-9e83ee1e4f60",
        "是否成交": true,
        "竞拍人数": null,
        "出价人数": 0,
        "地点": "河南省 信阳市 潢川县 世博国际城一期三号楼",
        "所属小区": "世博国际城一期",
        "省份": "河南省",
        "城市": "信阳市",
        "区": "潢川县",
        "最靠近商圈": "潢川县中心城区",
        "建筑面积": null,
        "单价": 0,
        "is_processed": true,
        "detail_captured": true
    },
    {
        "id": 646450132666,
        "市场评估价": 0,
        "起拍价格": 0,
        "成交价格": 700000,
        "交易时间": "2021-08-08 10:55:50",
        "原始网站": "https://sf-item.taobao.com/sf_item/646450132666.htm?track_id=344b990a-67b6-4a2d-9c53-71e646444610",
        "是否成交": true,
        "竞拍人数": 0,
        "出价人数": 19,
        "地点": "安徽省淮南市大通区东方城市花园瀚城二期B2栋106室",
        "所属小区": "东方城市花园瀚城",
        "省份": "安徽省",
        "城市": "淮南市",
        "区": "大通区",
        "最靠近商圈": null,
        "建筑面积": 90,
        "单价": 7777.78,
        "is_processed": true,
        "detail_captured": true
    },
    {
        "id": 650632155471,
        "市场评估价": 513975.33,
        "起拍价格": 359783,
        "成交价格": 542783,
        "交易时间": "2021-08-08 10:00:00",
        "原始网站": "https://sf-item.taobao.com/sf_item/650632155471.htm?track_id=72564c4e-ad8d-4939-b974-3fd618b1b5a3",
        "是否成交": true,
        "竞拍人数": 47,
        "出价人数": 47,
        "地点": "江西省 南昌市 西湖区 南昌市西湖区西湖路15号房产",
        "所属小区": "西湖路15号",
        "省份": "江西省",
        "城市": "南昌市",
        "区": "西湖区",
        "最靠近商圈": "西湖商圈",
        "建筑面积": 46.61,
        "单价": 11646.48,
        "is_processed": true,
        "detail_captured": true
    },
    {
        "id": 651451570861,
        "市场评估价": 243701,
        "起拍价格": 156000,
        "成交价格": 199000,
        "交易时间": "2021-08-08 10:00:34",
        "原始网站": "https://sf-item.taobao.com/sf_item/651451570861.htm?track_id=3aea75c2-9108-4f12-8e87-83844a89de4b",
        "是否成交": true,
        "竞拍人数": 0,
        "出价人数": 37,
        "地点": "吉林省 吉林市 磐石市 位于磐石市站前广场南侧、202国道东侧站前广场小区一期1号楼，房号2208020100100010212002",
        "所属小区": "站前广场小区",
        "省份": "吉林省",
        "城市": "吉林市",
        "区": "磐石市",
        "最靠近商圈": "站前广场",
        "建筑面积": 119.52,
        "单价": 1664.81,
        "is_processed": true,
        "detail_captured": true
    },
    {
        "id": 650658300659,
        "市场评估价": 174791,
        "起拍价格": 112000,
        "成交价格": 146000,
        "交易时间": "2021/08/08 10:23:48",
        "原始网站": "https://sf-item.taobao.com/sf_item/650658300659.htm?track_id=3aea75c2-9108-4f12-8e87-83844a89de4b",
        "是否成交": true,
        "竞拍人数": 19,
        "出价人数": 33,
        "地点": "吉林省吉林市磐石市站前广场南侧、202国道东侧站前广场小区一期1号楼，房号2208020100100010211001",
        "所属小区": "站前广场小区",
        "省份": "吉林省",
        "城市": "吉林市",
        "区": "磐石市",
        "最靠近商圈": "站前广场板块",
        "建筑面积": 86.53,
        "单价": 1687.27,
        "is_processed": true,
        "detail_captured": true
    },
    {
        "id": 650665804907,
        "市场评估价": 137047,
        "起拍价格": 87760,
        "成交价格": 87760,
        "交易时间": "2021/08/08 10:01:49",
        "原始网站": "https://sf-item.taobao.com/sf_item/650665804907.htm?track_id=51460f9e-9329-4538-b1a6-bc54a0f63554",
        "是否成交": true,
        "竞拍人数": 1,
        "出价人数": 1,
        "地点": "吉林省吉林市磐石市站前广场南侧、202国道东侧站前广场小区一期8号楼",
        "所属小区": "站前广场小区",
        "省份": "吉林省",
        "城市": "吉林市",
        "区": "磐石市",
        "最靠近商圈": "站前广场板块",
        "建筑面积": 70.57,
        "单价": 1243.59,
        "is_processed": true,
        "detail_captured": true
    },
    {
        "id": 649493844558,
        "市场评估价": 400000,
        "起拍价格": 400000,
        "成交价格": 444000,
        "交易时间": "2021/08/08 10:21:57",
        "原始网站": "https://sf-item.taobao.com/sf_item/649493844558.htm?track_id=18ba4557-54f1-4ae6-88c0-6310eb58843b",
        "是否成交": true,
        "竞拍人数": 12,
        "出价人数": 12,
        "地点": "江西省 上饶市 婺源县 紫阳镇种德里路6号楼137室",
        "所属小区": null,
        "省份": "江西省",
        "城市": "上饶市",
        "区": "婺源县",
        "最靠近商圈": "紫阳镇中心商圈",
        "建筑面积": null,
        "单价": 0,
        "is_processed": true,
        "detail_captured": true
    },
    {
        "id": 649899293423,
        "市场评估价": 250000,
        "起拍价格": null,
        "成交价格": 250000,
        "交易时间": "2021-08-08 10:00:42",
        "原始网站": "https://sf-item.taobao.com/sf_item/649899293423.htm?track_id=18ba4557-54f1-4ae6-88c0-6310eb58843b",
        "是否成交": true,
        "竞拍人数": null,
        "出价人数": null,
        "地点": "江西省 上饶市 婺源县 紫阳镇种德里路6号楼136室",
        "所属小区": null,
        "省份": "江西省",
        "城市": "上饶市",
        "区": "婺源县",
        "最靠近商圈": null,
        "建筑面积": null,
        "单价": 0,
        "is_processed": true,
        "detail_captured": true
    },
    {
        "id": 650274778513,
        "市场评估价": 1356100,
        "起拍价格": 949300,
        "成交价格": 949300,
        "交易时间": "2021-08-08T10:00:00",
        "原始网站": "https://sf-item.taobao.com/sf_item/650274778513.htm?track_id=890c74c1-62ef-4218-b495-1c617fd5df70",
        "是否成交": true,
        "竞拍人数": 1,
        "出价人数": 1,
        "地点": "福建省 龙岩市 连城县 连峰镇南门小区F幢1层4号店铺",
        "所属小区": "南门小区",
        "省份": "福建省",
        "城市": "龙岩市",
        "区": "连城县",
        "最靠近商圈": "连城",
        "建筑面积": 59.41,
        "单价": 15980.44,
        "is_processed": true,
        "detail_captured": true
    },
    {
        "id": 650645307023,
        "市场评估价": 311500,
        "起拍价格": 218100,
        "成交价格": 218100,
        "交易时间": "2021-08-08",
        "原始网站": "https://sf-item.taobao.com/sf_item/650645307023.htm?track_id=890c74c1-62ef-4218-b495-1c617fd5df70",
        "是否成交": true,
        "竞拍人数": 1,
        "出价人数": 1,
        "地点": "福建省龙岩市连城县连峰镇北大东路冠华小区E1幢1层7号店",
        "所属小区": "冠华小区",
        "省份": "福建省",
        "城市": "龙岩市",
        "区": "连城县",
        "最靠近商圈": null,
        "建筑面积": 41.43,
        "单价": 5267.1,
        "is_processed": true,
        "detail_captured": true
    },
    {
        "id": 649886689268,
        "市场评估价": 2356322,
        "起拍价格": 1649425.4,
        "成交价格": 1833425.4,
        "交易时间": "2021/08/08 10:37:33",
        "原始网站": "https://sf-item.taobao.com/sf_item/649886689268.htm?track_id=d43b7ad7-834f-4642-9783-a454b317a722",
        "是否成交": true,
        "竞拍人数": null,
        "出价人数": null,
        "地点": "江西省 南昌市 南昌县 南昌市南昌县莲塘镇澄湖北大道588号语花庭5栋五单元102室",
        "所属小区": "语花庭",
        "省份": "江西省",
        "城市": "南昌市",
        "区": "南昌县",
        "最靠近商圈": "莲塘镇",
        "建筑面积": 219.09,
        "单价": 8370.45,
        "is_processed": true,
        "detail_captured": true
    },
    {
        "id": 650626960014,
        "市场评估价": 1605480,
        "起拍价格": 0,
        "成交价格": 1805480,
        "交易时间": "2021/08/08 10:05:29",
        "原始网站": "https://sf-item.taobao.com/sf_item/650626960014.htm?track_id=adff0cea-6781-4c52-8fdf-35e268c233c3",
        "是否成交": true,
        "竞拍人数": 0,
        "出价人数": 26,
        "地点": "大庆市开发区秀水路1号沿湖城听涛湾1-1-104室",
        "所属小区": "沿湖城听涛湾",
        "省份": "黑龙江省",
        "城市": "大庆市",
        "区": "萨尔图区",
        "最靠近商圈": "高新区",
        "建筑面积": null,
        "单价": 0,
        "is_processed": true,
        "detail_captured": true
    },
    {
        "id": 649398612384,
        "市场评估价": 3165800,
        "起拍价格": 2530000,
        "成交价格": 2710000,
        "交易时间": "2021-08-08",
        "原始网站": "https://sf-item.taobao.com/sf_item/649398612384.htm?track_id=8fd76efe-f991-4a2f-bfed-d287c33181d0",
        "是否成交": true,
        "竞拍人数": 16,
        "出价人数": 16,
        "地点": "江西省吉安市吉水县吉水县城石阳小区25号1-4层",
        "所属小区": "石阳小区",
        "省份": "江西省",
        "城市": "吉安市",
        "区": "吉水县",
        "最靠近商圈": "吉水县城中心商圈",
        "建筑面积": 422.1,
        "单价": 6420.42,
        "is_processed": true,
        "detail_captured": true
    },
    {
        "id": 651443990729,
        "市场评估价": 436551.6,
        "起拍价格": 436551.6,
        "成交价格": 436551.6,
        "交易时间": "2021/08/08",
        "原始网站": "https://sf-item.taobao.com/sf_item/651443990729.htm?track_id=1d925fa0-777f-48ee-aac7-9ce338c3662d",
        "是否成交": true,
        "竞拍人数": 0,
        "出价人数": 1,
        "地点": "内蒙古自治区鄂尔多斯市达拉特旗树林召镇文苑小区南门D-5点式楼1号",
        "所属小区": "文苑小区",
        "省份": "内蒙古自治区",
        "城市": "鄂尔多斯市",
        "区": "达拉特旗",
        "最靠近商圈": "树林召镇",
        "建筑面积": 59.71,
        "单价": 7311.27,
        "is_processed": true,
        "detail_captured": true
    },
    {
        "id": 650570187944,
        "市场评估价": null,
        "起拍价格": 1299312,
        "成交价格": 1299312,
        "交易时间": "2021/08/08 10:00:00",
        "原始网站": "https://sf-item.taobao.com/sf_item/650570187944.htm?track_id=c9cdb66c-3285-47db-a74b-63df59e365bb",
        "是否成交": true,
        "竞拍人数": 1,
        "出价人数": 1,
        "地点": "位于武汉市江岸区兴业路191号银湖湾三和福邸A栋3层（2-3）商2室商铺",
        "所属小区": "银湖湾三和福邸",
        "省份": "湖北省",
        "城市": "武汉市",
        "区": "江岸区",
        "最靠近商圈": "后湖",
        "建筑面积": null,
        "单价": 0,
        "is_processed": true,
        "detail_captured": true
    },
    {
        "id": 649840286255,
        "市场评估价": 0,
        "起拍价格": 180740,
        "成交价格": 288740,
        "交易时间": "2021/08/08 10:33:57",
        "原始网站": "https://sf-item.taobao.com/sf_item/649840286255.htm?track_id=25b889b7-de44-4b43-9bfa-f50ec8c63cc6",
        "是否成交": true,
        "竞拍人数": 0,
        "出价人数": 44,
        "地点": "湖北省 武汉市 江岸区 沿江大道227-228号江景大厦地下层76室",
        "所属小区": "江景大厦",
        "省份": "湖北省",
        "城市": "武汉市",
        "区": "江岸区",
        "最靠近商圈": "江汉路",
        "建筑面积": 11.5,
        "单价": 25107.83,
        "is_processed": true,
        "detail_captured": true
    },
    {
        "id": 649067168287,
        "市场评估价": null,
        "起拍价格": 193550,
        "成交价格": 299550,
        "交易时间": "2021-08-08 10:27:25",
        "原始网站": "https://sf-item.taobao.com/sf_item/649067168287.htm?track_id=e0f22324-840e-488f-9b14-49eb8ef12f82",
        "是否成交": true,
        "竞拍人数": null,
        "出价人数": 36,
        "地点": "湖北省 武汉市 江岸区 沿江大道227-228号江景大厦车库3室",
        "所属小区": "江景大厦",
        "省份": "湖北省",
        "城市": "武汉市",
        "区": "江岸区",
        "最靠近商圈": "江岸沿江",
        "建筑面积": 11.5,
        "单价": 26048.7,
        "is_processed": true,
        "detail_captured": true
    },
    {
        "id": 649426536118,
        "市场评估价": 0,
        "起拍价格": 1528352,
        "成交价格": 1528352,
        "交易时间": "2021/08/08 10:00:00",
        "原始网站": "https://sf-item.taobao.com/sf_item/649426536118.htm?track_id=681a6d40-510b-4672-8844-095d5257818f",
        "是否成交": true,
        "竞拍人数": 0,
        "出价人数": 0,
        "地点": "湖北省武汉市江岸区兴业路191号银湖湾三和福邸B栋501住宅",
        "所属小区": "银湖湾三和福邸",
        "省份": "湖北省",
        "城市": "武汉市",
        "区": "江岸区",
        "最靠近商圈": "后湖商圈",
        "建筑面积": null,
        "单价": 0,
        "is_processed": true,
        "detail_captured": true
    },
    {
        "id": 649426564121,
        "市场评估价": null,
        "起拍价格": 1142064,
        "成交价格": 1142064,
        "交易时间": "2021-08-08 10:00:00",
        "原始网站": "https://sf-item.taobao.com/sf_item/649426564121.htm?track_id=681a6d40-510b-4672-8844-095d5257818f",
        "是否成交": true,
        "竞拍人数": null,
        "出价人数": null,
        "地点": "湖北省 武汉市 江岸区 位于武汉市江岸区兴业路191号银湖湾三和福邸B栋502住宅",
        "所属小区": "银湖湾三和福邸",
        "省份": "湖北省",
        "城市": "武汉市",
        "区": "江岸区",
        "最靠近商圈": "后湖",
        "建筑面积": null,
        "单价": 0,
        "is_processed": true,
        "detail_captured": true
    },
    {
        "id": 649841721789,
        "市场评估价": null,
        "起拍价格": 1142064,
        "成交价格": 1142064,
        "交易时间": "2021-08-08 10:00:00",
        "原始网站": "https://sf-item.taobao.com/sf_item/649841721789.htm?track_id=681a6d40-510b-4672-8844-095d5257818f",
        "是否成交": true,
        "竞拍人数": null,
        "出价人数": null,
        "地点": "湖北省 武汉市 江岸区 位于武汉市江岸区兴业路191号银湖湾三和福邸B栋1502住宅",
        "所属小区": "银湖湾三和福邸",
        "省份": "湖北省",
        "城市": "武汉市",
        "区": "江岸区",
        "最靠近商圈": "后湖",
        "建筑面积": null,
        "单价": 0,
        "is_processed": true,
        "detail_captured": true
    },
    {
        "id": 650569387803,
        "市场评估价": null,
        "起拍价格": 1528352,
        "成交价格": 1528352,
        "交易时间": "2021-08-08 10:00:00",
        "原始网站": "https://sf-item.taobao.com/sf_item/650569387803.htm?track_id=681a6d40-510b-4672-8844-095d5257818f",
        "是否成交": true,
        "竞拍人数": null,
        "出价人数": null,
        "地点": "湖北省 武汉市 江岸区 兴业路191号银湖湾三和福邸B栋1501住宅",
        "所属小区": "银湖湾三和福邸",
        "省份": "湖北省",
        "城市": "武汉市",
        "区": "江岸区",
        "最靠近商圈": "后湖",
        "建筑面积": null,
        "单价": 0,
        "is_processed": true,
        "detail_captured": true
    },
    {
        "id": 650569427172,
        "市场评估价": null,
        "起拍价格": 1159536,
        "成交价格": 1159536,
        "交易时间": "2021/08/08 10:00:00",
        "原始网站": "https://sf-item.taobao.com/sf_item/650569427172.htm?track_id=681a6d40-510b-4672-8844-095d5257818f",
        "是否成交": true,
        "竞拍人数": null,
        "出价人数": 1,
        "地点": "湖北省武汉市江岸区兴业路191号银湖湾三和福邸B栋503住宅",
        "所属小区": "银湖湾三和福邸",
        "省份": "湖北省",
        "城市": "武汉市",
        "区": "江岸区",
        "最靠近商圈": null,
        "建筑面积": null,
        "单价": 0,
        "is_processed": true,
        "detail_captured": true
    }
]